LICENSE
MANIFEST.in
README.md
pyproject.toml
requirements.txt
setup.py
hypertrees/__init__.py
hypertrees/_version.py
hypertrees/base.py
hypertrees/melter.py
hypertrees.egg-info/PKG-INFO
hypertrees.egg-info/SOURCES.txt
hypertrees.egg-info/dependency_links.txt
hypertrees.egg-info/not-zip-safe
hypertrees.egg-info/requires.txt
hypertrees.egg-info/top_level.txt
hypertrees/ensemble/__init__.py
hypertrees/ensemble/_forest.py
hypertrees/matrix_factorization/__init__.py
hypertrees/matrix_factorization/_nrlmf.py
hypertrees/model_selection/__init__.py
hypertrees/model_selection/_search.py
hypertrees/model_selection/_split.py
hypertrees/model_selection/_validation.py
hypertrees/tree/__init__.py
hypertrees/tree/_nd_classes.py
hypertrees/tree/_nd_criterion.c
hypertrees/tree/_nd_criterion.pxd
hypertrees/tree/_nd_criterion.pyx
hypertrees/tree/_nd_splitter.c
hypertrees/tree/_nd_splitter.pxd
hypertrees/tree/_nd_splitter.pyx
hypertrees/tree/_nd_tree.cpp
hypertrees/tree/_nd_tree.pxd
hypertrees/tree/_nd_tree.pyx
hypertrees/tree/_semisupervised_classes.py
hypertrees/tree/_semisupervised_criterion.c
hypertrees/tree/_semisupervised_criterion.pxd
hypertrees/tree/_semisupervised_criterion.pyx
hypertrees/tree/setup.py
hypertrees/utils/__init__.py