Metadata-Version: 2.1
Name: hypertrees
Version: 0.4.0a0
Summary: HyperTrees in Python.
Home-page: http://github.com/pedroilidio/hypertrees
Author: Pedro Ilídio
Author-email: pedrilidio@gmail.com
License: new BSD
Platform: UNKNOWN
License-File: LICENSE
